README
setup.py
leclerc/__init__.py
leclerc/monte_databricks.py
leclerc/montecarlinator.py
leclerc/pert.py
leclerc.egg-info/PKG-INFO
leclerc.egg-info/SOURCES.txt
leclerc.egg-info/dependency_links.txt
leclerc.egg-info/top_level.txt