Metadata-Version: 2.1
Name: leclerc
Version: 0.1.5
Summary: Leclerc conducts a montecarlo analysis on a range of function files that involve formula derivation
Home-page: https://pypi.org/project/leclerc/
Author: Luke Marhsall and Hoshang Mehta
Author-email: luke.marshall@suncable.energy
License: Open Source
Keywords: Montecarlo,levelised cost
Platform: UNKNOWN
Classifier: Development Status :: 3 - Alpha
Classifier: Topic :: Utilities
Classifier: License :: OSI Approved :: BSD License
